framework/StatLogger.py
framework/TraceLogger.py
framework/__init__.py
framework/afts.py
framework/afts_client.py
framework/common.py
framework/errors.py
framework/framework.py
framework/schema.py
framework/util.py
cspframework-0.1.0.dist-info/METADATA
cspframework-0.1.0.dist-info/WHEEL
cspframework-0.1.0.dist-info/top_level.txt
cspframework-0.1.0.dist-info/RECORD
