Metadata-Version: 2.1
Name: cspframework
Version: 0.1.0
Summary: A CSP framework on Maya platform for algorithm deployment and inference.
Home-page: https://code.alipay.com/algo_project/xframework
Author: qinzhong.wangqz
Author-email: qinzhong.wangqz@antgroup.com
Classifier: Programming Language :: Python :: 3
Classifier: License :: OSI Approved :: MIT License
Classifier: Operating System :: OS Independent
Requires-Python: >=3.6
